parameterizations/__init__.py
parameterizations/shapes.py
parameterizations/test_shapes.py
ucar_parameterizations_assignment_ap-0.0.3.dist-info/METADATA
ucar_parameterizations_assignment_ap-0.0.3.dist-info/WHEEL
ucar_parameterizations_assignment_ap-0.0.3.dist-info/top_level.txt
ucar_parameterizations_assignment_ap-0.0.3.dist-info/RECORD
